mne_videobrowser/__init__.py
mne_videobrowser/audio_player.py
mne_videobrowser/browser_synchronizer.py
mne_videobrowser/raw_timestamp_computaton.py
mne_videobrowser/synced_raw_media_browser.py
mne_videobrowser/timestamp_aligner.py
mne_videobrowser/browsers/__init__.py
mne_videobrowser/browsers/audio_browser.py
mne_videobrowser/browsers/gui_utils.py
mne_videobrowser/browsers/raw_browser_manager.py
mne_videobrowser/browsers/syncable_browser.py
mne_videobrowser/browsers/time_selector.py
mne_videobrowser/browsers/video_browser.py
mne_videobrowser/icons/info.png
mne_videobrowser/media/__init__.py
mne_videobrowser/media/_helsinki_videomeg_file_utils.py
mne_videobrowser/media/audio.py
mne_videobrowser/media/video.py
mne_videobrowser-0.1.8.dist-info/METADATA
mne_videobrowser-0.1.8.dist-info/WHEEL
mne_videobrowser-0.1.8.dist-info/licenses/LICENSE
mne_videobrowser-0.1.8.dist-info/RECORD
