Metadata-Version: 2.4
Name: mne-videobrowser
Version: 0.1.8
Summary: Python package for browsing video and audio time-synchronized to MEG/EEG data
Project-URL: Repository, https://github.com/ttaiv/mne-videobrowser
Project-URL: Documentation, https://mne-videobrowser.readthedocs.io/
Author-email: Teemu Taivainen <ttaiv@outlook.com>
License-Expression: BSD-3-Clause
License-File: LICENSE
Keywords: audio,brain,eeg,meg,neuroimaging,neuroscience,video
Classifier: Intended Audience :: Developers
Classifier: Intended Audience :: Science/Research
Classifier: License :: OSI Approved
Classifier: Operating System :: MacOS
Classifier: Operating System :: Microsoft :: Windows
Classifier: Operating System :: POSIX
Classifier: Operating System :: Unix
Classifier: Programming Language :: Python :: 3
Classifier: Topic :: Multimedia :: Sound/Audio
Classifier: Topic :: Multimedia :: Video :: Display
Classifier: Topic :: Scientific/Engineering
Requires-Python: >=3.10
Requires-Dist: mne-qt-browser>=0.7
Requires-Dist: mne>=1.10
Requires-Dist: opencv-python-headless>=4.8
Requires-Dist: pyqt5>=5.15
Requires-Dist: sounddevice>=0.5
Provides-Extra: dev
Requires-Dist: pydata-sphinx-theme; extra == 'dev'
Requires-Dist: pyqt5-stubs; extra == 'dev'
Requires-Dist: pyright; extra == 'dev'
Requires-Dist: pytest; extra == 'dev'
Requires-Dist: ruff; extra == 'dev'
Requires-Dist: sphinx; extra == 'dev'
